{"id":"power_dispatch_scada","name":"电力调度SCADA","category":"综合监控","keywords":["调度","SCADA","地理接线图","负荷","频率"],"size":"1920x1080","style":{"theme":"tech-blue","primary_color":"#00d4ff","bg_color":"#0a1628"},"pages":[{"name":"调度","sections":[{"name":"地理图","zone":"center","position":{"x":20,"y":80,"w":1300,"h":600},"components":[{"type":"BaiduMap3D","content":{"title":"电网地理接线图"}}]},{"name":"负荷","zone":"right","position":{"x":1340,"y":80,"w":560,"h":600},"components":[{"type":"DvBorderBox1","content":{"title":"区域负荷"}},{"type":"ViewChartGauge","content":{"title":"频率","unit":"Hz","range":[49.5,50.5]}},{"type":"ViewSvgText","content":{"text":"总负荷: {{total}}MW"}},{"type":"ViewSvgText","content":{"text":"备用容量: {{reserve}}MW"}}]}]}]}
